pytest_dotenv/__init__.py
pytest_dotenv/plugin.py
pytest_dotenv-0.5.1.dist-info/LICENSE
pytest_dotenv-0.5.1.dist-info/METADATA
pytest_dotenv-0.5.1.dist-info/WHEEL
pytest_dotenv-0.5.1.dist-info/entry_points.txt
pytest_dotenv-0.5.1.dist-info/top_level.txt
pytest_dotenv-0.5.1.dist-info/RECORD
